[
  { "id": "egg",                "name": "Digi Egg",          "stage": "egg",     "sprite": { "idle": "egg/idle.png" } },

  { "id": "botamon",            "name": "Botamon",           "stage": "fresh",   "sprite": { "idle": "botamon/idle.png", "walk": "botamon/walk.png" } },
  { "id": "kuramon",            "name": "Kuramon",           "stage": "fresh",   "sprite": { "idle": "kuramon/idle.png", "walk": "kuramon/walk.png" } },
  { "id": "poyomon",            "name": "Poyomon",           "stage": "fresh",   "sprite": { "idle": "poyomon/idle.png", "walk": "poyomon/walk.png" } },

  { "id": "koromon",            "name": "Koromon",           "stage": "baby",    "sprite": { "idle": "koromon/idle.png", "walk": "koromon/walk.png" } },
  { "id": "tsunomon",           "name": "Tsunomon",          "stage": "baby",    "sprite": { "idle": "tsunomon/idle.png", "walk": "tsunomon/walk.png" } },
  { "id": "tokomon",            "name": "Tokomon",           "stage": "baby",    "sprite": { "idle": "tokomon/idle.png", "walk": "tokomon/walk.png" } },

  { "id": "agumon",             "name": "Agumon",            "stage": "child",   "sprite": { "idle": "agumon/idle.png", "walk": "agumon/walk.png" }, "attribute": "vaccine" },
  { "id": "gabumon",            "name": "Gabumon",           "stage": "child",   "sprite": { "idle": "gabumon/idle.png", "walk": "gabumon/walk.png" }, "attribute": "data" },
  { "id": "patamon",            "name": "Patamon",           "stage": "child",   "sprite": { "idle": "patamon/idle.png", "walk": "patamon/walk.png" }, "attribute": "vaccine" },

  { "id": "greymon",            "name": "Greymon",           "stage": "adult",   "sprite": { "idle": "greymon/idle.png", "walk": "greymon/walk.png" }, "attribute": "vaccine" },
  { "id": "monochromon",        "name": "Monochromon",       "stage": "adult",   "sprite": { "idle": "monochromon/idle.png", "walk": "monochromon/walk.png" }, "attribute": "data" },
  { "id": "darktyrannomon",     "name": "DarkTyrannomon",    "stage": "adult",   "sprite": { "idle": "darktyrannomon/idle.png", "walk": "darktyrannomon/walk.png" }, "attribute": "virus" },
  { "id": "garurumon",          "name": "Garurumon",         "stage": "adult",   "sprite": { "idle": "garurumon/idle.png", "walk": "garurumon/walk.png" }, "attribute": "vaccine" },
  { "id": "leomon",             "name": "Leomon",            "stage": "adult",   "sprite": { "idle": "leomon/idle.png", "walk": "leomon/walk.png" }, "attribute": "vaccine" },
  { "id": "saberdramon",        "name": "Saberdramon",       "stage": "adult",   "sprite": { "idle": "saberdramon/idle.png", "walk": "saberdramon/walk.png" }, "attribute": "data" },
  { "id": "ogremon",            "name": "Ogremon",           "stage": "adult",   "sprite": { "idle": "ogremon/idle.png", "walk": "ogremon/walk.png" }, "attribute": "virus" },
  { "id": "angemon",            "name": "Angemon",           "stage": "adult",   "sprite": { "idle": "angemon/idle.png", "walk": "angemon/walk.png" }, "attribute": "vaccine" },
  { "id": "birdramon",          "name": "Birdramon",         "stage": "adult",   "sprite": { "idle": "birdramon/idle.png", "walk": "birdramon/walk.png" }, "attribute": "vaccine" },
  { "id": "centarumon",         "name": "Centarumon",        "stage": "adult",   "sprite": { "idle": "centarumon/idle.png", "walk": "centarumon/walk.png" }, "attribute": "data" },
  { "id": "devimon",            "name": "Devimon",           "stage": "adult",   "sprite": { "idle": "devimon/idle.png", "walk": "devimon/walk.png" }, "attribute": "virus" },
  { "id": "raremon",            "name": "Raremon",           "stage": "adult",   "sprite": { "idle": "raremon/idle.png", "walk": "raremon/walk.png" }, "attribute": "virus" },
  { "id": "numemon",            "name": "Numemon",           "stage": "adult",   "sprite": { "idle": "numemon/idle.png", "walk": "numemon/walk.png" }, "attribute": "virus" },

  { "id": "metalgreymon",       "name": "MetalGreymon",      "stage": "perfect", "sprite": { "idle": "metalgreymon/idle.png", "walk": "metalgreymon/walk.png" }, "attribute": "vaccine" },
  { "id": "mammothmon",         "name": "Mammothmon",        "stage": "perfect", "sprite": { "idle": "mammothmon/idle.png", "walk": "mammothmon/walk.png" }, "attribute": "vaccine" },
  { "id": "metaltyrannomon",    "name": "MetalTyrannomon",   "stage": "perfect", "sprite": { "idle": "metaltyrannomon/idle.png", "walk": "metaltyrannomon/walk.png" }, "attribute": "virus" },
  { "id": "skullgreymon",       "name": "SkullGreymon",      "stage": "perfect", "sprite": { "idle": "skullgreymon/idle.png", "walk": "skullgreymon/walk.png" }, "attribute": "virus" },
  { "id": "weregarurumon",      "name": "WereGarurumon",     "stage": "perfect", "sprite": { "idle": "weregarurumon/idle.png", "walk": "weregarurumon/walk.png" }, "attribute": "vaccine" },
  { "id": "weregarurumonblack", "name": "WereGarurumonBlack","stage": "perfect", "sprite": { "idle": "weregarurumonblack/idle.png", "walk": "weregarurumonblack/walk.png" }, "attribute": "virus" },
  { "id": "saberleomon",        "name": "SaberLeomon",       "stage": "perfect", "sprite": { "idle": "saberleomon/idle.png", "walk": "saberleomon/walk.png" }, "attribute": "data" },
  { "id": "garudamon",          "name": "Garudamon",         "stage": "perfect", "sprite": { "idle": "garudamon/idle.png", "walk": "garudamon/walk.png" }, "attribute": "vaccine" },
  { "id": "magnaangemon",       "name": "MagnaAngemon",      "stage": "perfect", "sprite": { "idle": "magnaangemon/idle.png", "walk": "magnaangemon/walk.png" }, "attribute": "vaccine" },
  { "id": "vamdemon",           "name": "Vamdemon",          "stage": "perfect", "sprite": { "idle": "vamdemon/idle.png", "walk": "vamdemon/walk.png" }, "attribute": "virus" },
  { "id": "ladydevimon",        "name": "LadyDevimon",       "stage": "perfect", "sprite": { "idle": "ladydevimon/idle.png", "walk": "ladydevimon/walk.png" }, "attribute": "virus" },
  { "id": "etemon",             "name": "Etemon",            "stage": "perfect", "sprite": { "idle": "etemon/idle.png", "walk": "etemon/walk.png" }, "attribute": "virus" },

  { "id": "wargreymon",         "name": "WarGreymon",        "stage": "mega",    "sprite": { "idle": "wargreymon/idle.png", "walk": "wargreymon/walk.png" }, "attribute": "vaccine" },
  { "id": "blackwargreymon",    "name": "BlackWarGreymon",   "stage": "mega",    "sprite": { "idle": "blackwargreymon/idle.png", "walk": "blackwargreymon/walk.png" }, "attribute": "virus" },
  { "id": "metalgarurumon",     "name": "MetalGarurumon",    "stage": "mega",    "sprite": { "idle": "metalgarurumon/idle.png", "walk": "metalgarurumon/walk.png" }, "attribute": "vaccine" },
  { "id": "seraphimon",         "name": "Seraphimon",        "stage": "mega",    "sprite": { "idle": "seraphimon/idle.png", "walk": "seraphimon/walk.png" }, "attribute": "vaccine" },
  { "id": "piedmon",            "name": "Piedmon",           "stage": "mega",    "sprite": { "idle": "piedmon/idle.png", "walk": "piedmon/walk.png" }, "attribute": "virus" }
]
